EffectiveCGaishanCChengxuDe50ZhongFangfa/README.md
EffectiveCGaishanCChengxuDe50ZhongFangfa/__init__.py
EffectiveCGaishanCChengxuDe50ZhongFangfa/__main__.py
EffectiveCGaishanCChengxuDe50ZhongFangfa/file.epub
EffectiveCGaishanCChengxuDe50ZhongFangfa/index.html
EffectiveCGaishanCChengxuDe50ZhongFangfa/css/__init__.py
EffectiveCGaishanCChengxuDe50ZhongFangfa/css/annotations.css
EffectiveCGaishanCChengxuDe50ZhongFangfa/css/main.css
EffectiveCGaishanCChengxuDe50ZhongFangfa/css/normalize.css
EffectiveCGaishanCChengxuDe50ZhongFangfa/css/popup.css
EffectiveCGaishanCChengxuDe50ZhongFangfa/font/__init__.py
EffectiveCGaishanCChengxuDe50ZhongFangfa/font/fontello.eot
EffectiveCGaishanCChengxuDe50ZhongFangfa/font/fontello.svg
EffectiveCGaishanCChengxuDe50ZhongFangfa/font/fontello.ttf
EffectiveCGaishanCChengxuDe50ZhongFangfa/font/fontello.woff
EffectiveCGaishanCChengxuDe50ZhongFangfa/img/__init__.py
EffectiveCGaishanCChengxuDe50ZhongFangfa/img/annotator-glyph-sprite.png
EffectiveCGaishanCChengxuDe50ZhongFangfa/img/annotator-icon-sprite.png
EffectiveCGaishanCChengxuDe50ZhongFangfa/img/apple-touch-icon.png
EffectiveCGaishanCChengxuDe50ZhongFangfa/img/cancelfullscreen.png
EffectiveCGaishanCChengxuDe50ZhongFangfa/img/close.png
EffectiveCGaishanCChengxuDe50ZhongFangfa/img/fullscreen.png
EffectiveCGaishanCChengxuDe50ZhongFangfa/img/loader.gif
EffectiveCGaishanCChengxuDe50ZhongFangfa/img/menu-icon.png
EffectiveCGaishanCChengxuDe50ZhongFangfa/img/save.png
EffectiveCGaishanCChengxuDe50ZhongFangfa/img/saved.png
EffectiveCGaishanCChengxuDe50ZhongFangfa/img/settings-s.png
EffectiveCGaishanCChengxuDe50ZhongFangfa/img/settings.png
EffectiveCGaishanCChengxuDe50ZhongFangfa/img/star.png
EffectiveCGaishanCChengxuDe50ZhongFangfa/js/__init__.py
EffectiveCGaishanCChengxuDe50ZhongFangfa/js/epub.js
EffectiveCGaishanCChengxuDe50ZhongFangfa/js/epub.min.js
EffectiveCGaishanCChengxuDe50ZhongFangfa/js/epub.min.map
EffectiveCGaishanCChengxuDe50ZhongFangfa/js/hooks.min.js
effective_c_gaishan_c_chengxu_de_50_zhong_fangfa-2024.3.1.0.dist-info/METADATA
effective_c_gaishan_c_chengxu_de_50_zhong_fangfa-2024.3.1.0.dist-info/WHEEL
effective_c_gaishan_c_chengxu_de_50_zhong_fangfa-2024.3.1.0.dist-info/entry_points.txt
effective_c_gaishan_c_chengxu_de_50_zhong_fangfa-2024.3.1.0.dist-info/top_level.txt
effective_c_gaishan_c_chengxu_de_50_zhong_fangfa-2024.3.1.0.dist-info/RECORD
